{
    "Config05Problem1_22": {
        "EarlyEnd": false,
        "Objective Criterion": 2,
        "Objective Value": 10610.621197,
        "Permutation": [
            45,
            22,
            23,
            25,
            31,
            24,
            46,
            38,
            39,
            48,
            47,
            2,
            49,
            1,
            0,
            12,
            36,
            37,
            42,
            41,
            40,
            16,
            43,
            44,
            19,
            20,
            21,
            17,
            18,
            7,
            8,
            9,
            10,
            6,
            4,
            5,
            3,
            33,
            35,
            32,
            34,
            13,
            15,
            14,
            27,
            11,
            29,
            26,
            28,
            30
        ],
        "BatchAllocation": [
            4,
            3,
            3,
            33,
            33,
            33,
            32,
            30,
            30,
            31,
            31,
            51,
            4,
            35,
            35,
            35,
            25,
            29,
            29,
            27,
            28,
            28,
            0,
            0,
            0,
            0,
            51,
            50,
            51,
            51,
            51,
            0,
            34,
            34,
            34,
            34,
            4,
            5,
            1,
            2,
            25,
            25,
            25,
            26,
            26,
            0,
            1,
            2,
            2,
            3
        ],
        "EndIndices": [
            5,
            7,
            10,
            13,
            16,
            17,
            -1,
            -1,
            -1,
            -1,
            -1,
            -1,
            -1,
            -1,
            -1,
            -1,
            -1,
            -1,
            -1,
            -1,
            -1,
            -1,
            -1,
            -1,
            -1,
            21,
            23,
            24,
            26,
            28,
            30,
            32,
            33,
            36,
            40,
            43,
            -1,
            -1,
            -1,
            -1,
            -1,
            -1,
            -1,
            -1,
            -1,
            -1,
            -1,
            -1,
            -1,
            -1,
            44,
            49,
            -1,
            -1,
            -1,
            -1,
            -1,
            -1,
            -1,
            -1,
            -1,
            -1,
            -1,
            -1,
            -1,
            -1,
            -1,
            -1,
            -1,
            -1,
            -1,
            -1,
            -1,
            -1,
            -1
        ],
        "Preprocess Time": 0.0,
        "Best Constructive Solution": 20930.616273,
        "Construction Runtime": 0.015002250671386719,
        "Improvement Runtime": 3600.8535561561584,
        "Overall Runtime": 3600.86855840683,
        "Feasible Assignments": 4432,
        "PerturbationsRounds": 3990,
        "AcceptanceCounter": 1521,
        "AcceptanceRate": 0.381203007518797,
        "PackingCalls Construction": 0,
        "PackingCalls Perturbation": 65255,
        "PackingCalls VNS": 7318,
        "NeighborhoodImprovements": {
            "3": 4,
            "2": 2,
            "0": 5,
            "1": 2
        },
        "SuccessfulPerturbations": 3989,
        "TimeToBest": 2.111118793487549,
        "TimeTo70": 9.178533554077148,
        "ObjectiveAt70": 10610.621197
    }
}